arcade_weaviate_api/__init__.py
arcade_weaviate_api/moar/Weaviate.json
arcade_weaviate_api/moar/openapi.json
arcade_weaviate_api/tools/__init__.py
arcade_weaviate_api/tools/request_body_schemas.py
arcade_weaviate_api/wrapper_tools/ActivateDatabaseUser.json
arcade_weaviate_api/wrapper_tools/AddPermissionsToRole.json
arcade_weaviate_api/wrapper_tools/AddPropertyToCollection.json
arcade_weaviate_api/wrapper_tools/AddReferenceToObject.json
arcade_weaviate_api/wrapper_tools/AssignRoleToGroup.json
arcade_weaviate_api/wrapper_tools/AssignRolesToUser.json
arcade_weaviate_api/wrapper_tools/BatchCreateReferences.json
arcade_weaviate_api/wrapper_tools/BatchRegisterObjects.json
arcade_weaviate_api/wrapper_tools/CancelBackup.json
arcade_weaviate_api/wrapper_tools/CancelReplication.json
arcade_weaviate_api/wrapper_tools/CancelReplicationOperation.json
arcade_weaviate_api/wrapper_tools/CheckBackupRestoreStatus.json
arcade_weaviate_api/wrapper_tools/CheckBackupStatus.json
arcade_weaviate_api/wrapper_tools/CheckRolePermission.json
arcade_weaviate_api/wrapper_tools/CheckWeaviateLiveness.json
arcade_weaviate_api/wrapper_tools/CheckWeaviateReadiness.json
arcade_weaviate_api/wrapper_tools/CreateAliasMapping.json
arcade_weaviate_api/wrapper_tools/CreateBackup.json
arcade_weaviate_api/wrapper_tools/CreateDatabaseUser.json
arcade_weaviate_api/wrapper_tools/CreateObjectInWeaviate.json
arcade_weaviate_api/wrapper_tools/CreateRoleWithPermissions.json
arcade_weaviate_api/wrapper_tools/CreateSchemaObject.json
arcade_weaviate_api/wrapper_tools/CreateTenants.json
arcade_weaviate_api/wrapper_tools/DeactivateDatabaseUser.json
arcade_weaviate_api/wrapper_tools/DeleteAlias.json
arcade_weaviate_api/wrapper_tools/DeleteAllReplications.json
arcade_weaviate_api/wrapper_tools/DeleteDataObject.json
arcade_weaviate_api/wrapper_tools/DeleteDatabaseUser.json
arcade_weaviate_api/wrapper_tools/DeleteMultipleObjects.json
arcade_weaviate_api/wrapper_tools/DeleteReferenceFromObject.json
arcade_weaviate_api-2.0.0.dist-info/METADATA
arcade_weaviate_api-2.0.0.dist-info/WHEEL
arcade_weaviate_api-2.0.0.dist-info/entry_points.txt
arcade_weaviate_api-2.0.0.dist-info/licenses/LICENSE
arcade_weaviate_api-2.0.0.dist-info/RECORD
